[{"__checker":{"show":1,"title":"<input type=\"checkbox\" class=\"all_products_checker\" \/>","desc":"Checkboxes for the products selection. Use SHIFT button on your keyboard to select multiple rows.","field_type":"none","type":"number","editable":false,"edit_view":"checkbox","order":false,"move":false,"direct":true,"shop_manager_visibility":1},"ID":{"show":1,"title":"ID","field_type":"field","type":"number","editable":false,"edit_view":"textinput","order":true,"move":false,"direct":true,"shop_manager_visibility":1},"_thumbnail_id":{"show":1,"title":"Thumbnail","field_type":"meta","type":"number","editable":true,"edit_view":"thumbnail","order":false,"direct":true,"shop_manager_visibility":1,"css_classes":""},"gallery":{"show":0,"title":"Gallery","desc":"Select any images which relate to the product","field_type":"gallery","type":"textinput","editable":true,"edit_view":"gallery_popup_editor","order":false,"direct":false,"prohibit_product_types":["variation"],"css_classes":"not-for-variations","shop_manager_visibility":1},"post_title":{"show":1,"title":"Title","field_type":"field","type":"string","editable":true,"edit_view":"textinput","order":true,"direct":true,"css_classes":"not-for-variations","shop_manager_visibility":1},"post_content":{"show":1,"title":"Description","field_type":"field","type":"string","editable":true,"edit_view":"popupeditor","order":false,"direct":true,"shop_manager_visibility":1},"post_excerpt":{"show":1,"title":"Short Desc.","field_type":"field","type":"string","editable":true,"edit_view":"popupeditor","order":false,"direct":false,"prohibit_product_types":["variation"],"css_classes":"not-for-variations","shop_manager_visibility":1},"post_name":{"show":0,"title":"Slug","field_type":"field","type":"string","editable":true,"edit_view":"textinput","sanitize":"urldecode","order":false,"direct":true,"prohibit_product_types":["variation"],"css_classes":"not-for-variations","shop_manager_visibility":1},"product_type":{"show":1,"title":"Type","field_type":"taxonomy","taxonomy":"product_type","type":"string","editable":true,"edit_view":"select","select_options":{"simple":"Simple","grouped":"Grouped","external":"External\/Affiliate","variable":"Variable"},"order":false,"direct":false,"prohibit_product_types":["variation"],"shop_manager_visibility":1},"post_status":{"show":1,"title":"Status","field_type":"field","type":"string","editable":true,"edit_view":"select","select_options":{"draft":"Draft","pending":"Pending Review","private":"Private","publish":"Published"},"order":false,"direct":true,"shop_manager_visibility":1},"catalog_visibility":{"show":0,"title":"Catalog Visibility","desc":"This setting determines which shop pages products will be listed on","field_type":"prop","type":"string","editable":true,"edit_view":"select","select_options":{"visible":"Shop and search results","catalog":"Shop only","search":"Search results only","hidden":"Hidden"},"order":false,"direct":true,"prohibit_product_types":["variation"],"css_classes":"not-for-variations","shop_manager_visibility":1},"featured":{"show":0,"title":"Featured","field_type":"prop","type":"string","editable":true,"edit_view":"switcher","select_options":{"yes":"Yes","no":"No"},"order":false,"direct":true,"prohibit_product_types":["variation"],"css_classes":"not-for-variations","shop_manager_visibility":1},"regular_price":{"show":1,"title":"Regular price","field_type":"prop","meta_key":"_regular_price","type":"number","sanitize":"floatval","editable":true,"edit_view":"textinput","order":true,"direct":true,"allow_product_types":["external","simple","variation"],"shop_manager_visibility":1},"sale_price":{"show":1,"title":"Sale price","field_type":"prop","meta_key":"_sale_price","type":"number","sanitize":"floatval","editable":true,"edit_view":"textinput","order":true,"direct":true,"allow_product_types":["external","simple","variation"],"shop_manager_visibility":1},"date_on_sale_from":{"show":0,"title":"Sale time from","desc":"The sale will end at the beginning of the set date","field_type":"prop","meta_key":"_sale_price_dates_from","type":"timestamp","set_day_end":false,"editable":true,"edit_view":"calendar","order":true,"direct":false,"allow_product_types":["external","simple","variation"],"shop_manager_visibility":1,"css_classes":""},"date_on_sale_to":{"show":0,"title":"Sale time to","field_type":"prop","meta_key":"_sale_price_dates_to","type":"timestamp","set_day_end":false,"editable":true,"edit_view":"calendar","order":true,"direct":false,"allow_product_types":["external","simple","variation"],"shop_manager_visibility":1,"css_classes":""},"downloadable":{"show":0,"title":"Downloadable","desc":"Downloadable products give access to a file upon purchase.","field_type":"prop","meta_key":"_downloadable","type":"string","editable":true,"edit_view":"switcher","select_options":{"yes":"Yes","no":"No"},"order":false,"direct":false,"allow_product_types":["simple","variation"],"shop_manager_visibility":1,"css_classes":""},"download_files":{"show":0,"title":"Down.Files","desc":"Downloadable files. Attention: maybe should be enabled Downloadable by logic!","field_type":"downloads","type":"string","editable":true,"edit_view":"downloads_popup_editor","order":false,"direct":true,"allow_product_types":["simple","variation"],"shop_manager_visibility":1,"css_classes":""},"download_limit":{"show":0,"title":"Download limit","desc":"Leave blank for unlimited re-downloads.  Attention: maybe should be enabled Downloadable by logic!","field_type":"prop","type":"number","editable":true,"edit_view":"textinput","sanitize":"intval","order":false,"direct":false,"allow_product_types":["simple","variation"],"shop_manager_visibility":1},"download_expiry":{"show":0,"title":"Download expiry","desc":"Enter the number of days before a download link expires, or leave blank. Attention: maybe should be enabled Downloadable by logic!","field_type":"prop","type":"number","editable":true,"edit_view":"textinput","sanitize":"intval","order":false,"direct":false,"allow_product_types":["simple","variation"],"shop_manager_visibility":1},"tax_status":{"show":0,"title":"Tax status","desc":"Define whether or not the entire product is taxable, or just the cost of shipping it.","field_type":"prop","type":"string","editable":false,"edit_view":"select","select_options":{"taxable":"Taxable","shipping":"Shipping only","none":"None"},"order":false,"direct":false,"allow_product_types":["simple","external","variable"],"css_classes":"not-for-variations","shop_manager_visibility":1},"tax_class":{"show":0,"title":"Tax class","desc":"Choose a tax class for this product. Tax classes are used to apply different tax rates specific to certain types of product.","field_type":"prop","type":"string","editable":true,"edit_view":"select","select_options":{"":"Standard","reduced-rate":"Reduced rate","zero-rate":"Zero rate"},"order":false,"direct":false,"allow_product_types":["simple","external","variable","variation"],"shop_manager_visibility":1,"css_classes":""},"sku":{"show":1,"title":"SKU","desc":"SKU refers to a Stock-keeping unit, a unique identifier for each distinct product and service that can be purchased.","field_type":"prop","meta_key":"_sku","type":"string","editable":true,"edit_view":"textinput","order":true,"direct":true,"shop_manager_visibility":1},"manage_stock":{"show":1,"title":"Manage stock","desc":"Enable stock management at product level. ATTENTION: if to set count of products in Stock quantity, Manage stock option automatically set as TRUE!","field_type":"prop","meta_key":"_manage_stock","type":"string","editable":true,"edit_view":"switcher","select_options":{"yes":"Yes","no":"No"},"order":true,"direct":true,"allow_product_types":["simple","variable","variation"],"shop_manager_visibility":1,"css_classes":""},"stock_quantity":{"show":1,"title":"In Stock","desc":"Stock quantity. If this is a variable product this value will be used to control stock for all variations, unless you define stock at variation level. ATTENTION: if to set count of products, Manage stock and Stock status options automatically set as TRUE!","field_type":"prop","meta_key":"_stock","type":"number","editable":true,"edit_view":"textinput","sanitize":"intval","order":true,"direct":false,"allow_product_types":["simple","variable","variation"],"shop_manager_visibility":1},"stock_status":{"show":1,"title":"Stock status","desc":"Controls whether or not the product is listed as in stock or out of stock on the frontend. Count products in stock can not be zero while activating!","field_type":"prop","meta_key":"_stock_status","type":"string","editable":true,"edit_view":"select","select_options":{"instock":"In stock","outofstock":"Out of stock","onbackorder":"On backorder"},"order":true,"direct":true,"allow_product_types":["simple","grouped","variation"],"shop_manager_visibility":1},"backorders":{"show":0,"title":"Allow backorders","desc":"If managing stock, this controls whether or not backorders are allowed. If enabled, stock quantity can go below 0. Does Not work if the product Manage stock option is not activated!","field_type":"prop","type":"string","editable":true,"edit_view":"select","select_options":{"no":"Do not allow","notify":"Allow, but notify customer","yes":"Allow"},"order":false,"direct":true,"allow_product_types":["simple","variation"],"shop_manager_visibility":1,"css_classes":""},"sold_individually":{"show":0,"title":"Sold individually","desc":"Enable this to only allow one of this item to be bought in a single order","field_type":"prop","meta_key":"_sold_individually","type":"string","editable":true,"edit_view":"switcher","select_options":{"yes":"Yes","no":"No"},"order":false,"direct":false,"allow_product_types":["simple","variable"],"css_classes":"not-for-variations","shop_manager_visibility":1},"weight":{"show":0,"title":"Weight","field_type":"prop","meta_key":"_weight","type":"number","editable":true,"edit_view":"textinput","sanitize":"floatval","order":true,"direct":true,"allow_product_types":["simple","variable","variation"],"shop_manager_visibility":1,"css_classes":""},"length":{"show":0,"title":"Length","field_type":"prop","meta_key":"_length","type":"number","editable":true,"edit_view":"textinput","sanitize":"floatval","order":true,"direct":true,"allow_product_types":["simple","variable","variation"],"shop_manager_visibility":1,"css_classes":""},"width":{"show":0,"title":"Width","field_type":"prop","meta_key":"_width","type":"number","editable":true,"edit_view":"textinput","sanitize":"floatval","order":true,"direct":true,"allow_product_types":["simple","variable","variation"],"shop_manager_visibility":1,"css_classes":""},"height":{"show":0,"title":"Height","field_type":"prop","meta_key":"_height","type":"number","editable":true,"edit_view":"textinput","sanitize":"floatval","order":true,"direct":false,"allow_product_types":["simple","variable","variation"],"shop_manager_visibility":1,"css_classes":""},"product_shipping_class":{"show":0,"title":"Shipping class","desc":"Shipping classes are used by certain shipping methods to group similar products.","field_type":"taxonomy","taxonomy":"product_shipping_class","type":"array","editable":true,"edit_view":"select","select_options":{"-1":"No shipping class"},"order":false,"direct":false,"allow_product_types":["simple","variable"],"css_classes":"not-for-variations","shop_manager_visibility":1},"upsell_ids":{"show":0,"title":"Upsells","desc":"Upsells are products which you recommend instead of the currently viewed product, for example, products that are more profitable or better quality or more expensive.","field_type":"upsells","type":"string","editable":true,"edit_view":"upsells_popup_editor","order":false,"direct":true,"prohibit_product_types":["variation"],"css_classes":"not-for-variations","shop_manager_visibility":1},"cross_sell_ids":{"show":0,"title":"Cross-sells","desc":"Cross-sells are products which you promote in the cart, based on the current product.","field_type":"cross_sells","type":"string","editable":true,"edit_view":"cross_sells_popup_editor","order":false,"direct":false,"allow_product_types":["simple","variable"],"css_classes":"not-for-variations","shop_manager_visibility":1},"grouped_ids":{"show":0,"title":"Grouped products","desc":"This lets you choose which products are part of this group.","field_type":"grouped","type":"string","editable":true,"edit_view":"grouped_popup_editor","order":false,"direct":true,"allow_product_types":["grouped"],"css_classes":"not-for-variations","shop_manager_visibility":1},"purchase_note":{"show":0,"title":"Purchase note","desc":"Enter an optional note to send the customer after purchase.","field_type":"prop","type":"string","editable":true,"edit_view":"popupeditor","order":false,"direct":false,"allow_product_types":["simple","variable"],"css_classes":"not-for-variations","shop_manager_visibility":1},"menu_order":{"show":0,"title":"Menu order","desc":"Custom ordering position.","field_type":"prop","type":"number","sanitize":"intval","editable":true,"edit_view":"textinput","order":true,"direct":true,"shop_manager_visibility":1},"reviews_allowed":{"show":0,"title":"Reviews allowed","field_type":"prop","type":"string","editable":true,"edit_view":"switcher","select_options":{"yes":"Yes","no":"No"},"order":false,"direct":false,"prohibit_product_types":["variation"],"css_classes":"not-for-variations","shop_manager_visibility":1},"product_url":{"show":0,"title":"Product url","desc":"External\/Affiliate product: External URL to the product","field_type":"prop","type":"string","editable":true,"edit_view":"url","sanitize":"esc_url","order":false,"direct":false,"allow_product_types":["external"],"css_classes":"not-for-variations","shop_manager_visibility":1},"button_text":{"show":0,"title":"Aff.Button text","desc":"External\/Affiliate product: This text will be shown on the button linking to the external product","field_type":"prop","type":"string","editable":true,"edit_view":"textinput","order":false,"direct":false,"allow_product_types":["external"],"css_classes":"not-for-variations","shop_manager_visibility":1},"virtual":{"show":0,"title":"Virtual","desc":"Virtual products are intangible and are not shipped.","field_type":"prop","type":"string","editable":true,"edit_view":"switcher","select_options":{"yes":"Yes","no":"No"},"order":false,"direct":false,"allow_product_types":["simple","variation"],"shop_manager_visibility":1,"css_classes":""},"post_author":{"show":0,"title":"Author","field_type":"field","type":"string","editable":true,"edit_view":"select","select_options":{"1":"realmag777","2":"shop-manager"},"order":false,"direct":false,"prohibit_product_types":["variation"],"css_classes":"not-for-variations","shop_manager_visibility":1},"total_sales":{"show":0,"title":"Total sales","desc":"Total count of the product sales","field_type":"prop","meta_key":"total_sales","type":"number","editable":true,"edit_view":"textinput","sanitize":"intval","order":true,"direct":false,"prohibit_product_types":["variation"],"css_classes":"not-for-variations","shop_manager_visibility":1},"review_count":{"show":0,"title":"Review count","desc":"How many times the products been reviewed by customers","field_type":"prop","meta_key":"_wc_review_count","type":"number","editable":true,"edit_view":"textinput","sanitize":"intval","order":true,"direct":false,"prohibit_product_types":["variation"],"css_classes":"not-for-variations","shop_manager_visibility":1},"average_rating":{"show":0,"title":"Average rating","desc":"Average rating of the product","field_type":"prop","meta_key":"_wc_average_rating","type":"number","editable":true,"edit_view":"textinput","sanitize":"floatval","order":true,"direct":false,"prohibit_product_types":["variation"],"css_classes":"not-for-variations","shop_manager_visibility":1},"post_date":{"show":0,"title":"Date Published","field_type":"field","type":"timestamp","set_day_end":false,"editable":true,"edit_view":"calendar","order":true,"direct":true,"prohibit_product_types":["variation"],"css_classes":"not-for-variations","shop_manager_visibility":1},"post_parent":{"show":0,"title":"Parent","field_type":"field","type":"number","editable":true,"edit_view":"textinput","sanitize":"intval","order":true,"direct":true,"allow_product_types":["variation"],"shop_manager_visibility":1}}]